{
  "docusaurus-plugin-content-docs": {
    "default": {
      "path": "/docs",
      "versions": [
        {
          "name": "current",
          "label": "Next",
          "isLast": false,
          "path": "/docs/next",
          "mainDocId": "rnf-intro",
          "docs": [
            {
              "id": "intro",
              "path": "/docs/next/intro",
              "sidebar": "tutorialSidebar"
            },
            {
              "id": "rnf-intro",
              "path": "/docs/next/rnf-intro",
              "sidebar": "tutorialSidebar"
            },
            {
              "id": "rpc-netty-framework-2.0/congratulations",
              "path": "/docs/next/rpc-netty-framework-2.0/congratulations",
              "sidebar": "tutorialSidebar"
            },
            {
              "id": "rpc-netty-framework-2.0/create-a-blog-post",
              "path": "/docs/next/rpc-netty-framework-2.0/create-a-blog-post",
              "sidebar": "tutorialSidebar"
            },
            {
              "id": "rpc-netty-framework-2.0/create-a-document",
              "path": "/docs/next/rpc-netty-framework-2.0/create-a-document",
              "sidebar": "tutorialSidebar"
            },
            {
              "id": "rpc-netty-framework-2.0/create-a-page",
              "path": "/docs/next/rpc-netty-framework-2.0/create-a-page",
              "sidebar": "tutorialSidebar"
            },
            {
              "id": "rpc-netty-framework-2.0/deploy-your-site",
              "path": "/docs/next/rpc-netty-framework-2.0/deploy-your-site",
              "sidebar": "tutorialSidebar"
            },
            {
              "id": "rpc-netty-framework-2.0/markdown-features",
              "path": "/docs/next/rpc-netty-framework-2.0/markdown-features",
              "sidebar": "tutorialSidebar"
            },
            {
              "id": "rpc-netty-framework-3.0/congratulations",
              "path": "/docs/next/rpc-netty-framework-3.0/congratulations",
              "sidebar": "tutorialSidebar"
            },
            {
              "id": "rpc-netty-framework-3.0/create-a-blog-post",
              "path": "/docs/next/rpc-netty-framework-3.0/create-a-blog-post",
              "sidebar": "tutorialSidebar"
            },
            {
              "id": "rpc-netty-framework-3.0/create-a-document",
              "path": "/docs/next/rpc-netty-framework-3.0/create-a-document",
              "sidebar": "tutorialSidebar"
            },
            {
              "id": "rpc-netty-framework-3.0/create-a-page",
              "path": "/docs/next/rpc-netty-framework-3.0/create-a-page",
              "sidebar": "tutorialSidebar"
            },
            {
              "id": "rpc-netty-framework-3.0/deploy-your-site",
              "path": "/docs/next/rpc-netty-framework-3.0/deploy-your-site",
              "sidebar": "tutorialSidebar"
            },
            {
              "id": "rpc-netty-framework-3.0/markdown-features",
              "path": "/docs/next/rpc-netty-framework-3.0/markdown-features",
              "sidebar": "tutorialSidebar"
            },
            {
              "id": "tutorial-basics/congratulations",
              "path": "/docs/next/tutorial-basics/congratulations",
              "sidebar": "tutorialSidebar"
            },
            {
              "id": "tutorial-basics/create-a-blog-post",
              "path": "/docs/next/tutorial-basics/create-a-blog-post",
              "sidebar": "tutorialSidebar"
            },
            {
              "id": "tutorial-basics/create-a-document",
              "path": "/docs/next/tutorial-basics/create-a-document",
              "sidebar": "tutorialSidebar"
            },
            {
              "id": "tutorial-basics/create-a-page",
              "path": "/docs/next/tutorial-basics/create-a-page",
              "sidebar": "tutorialSidebar"
            },
            {
              "id": "tutorial-basics/deploy-your-site",
              "path": "/docs/next/tutorial-basics/deploy-your-site",
              "sidebar": "tutorialSidebar"
            },
            {
              "id": "tutorial-basics/markdown-features",
              "path": "/docs/next/tutorial-basics/markdown-features",
              "sidebar": "tutorialSidebar"
            },
            {
              "id": "tutorial-extras/manage-docs-versions",
              "path": "/docs/next/tutorial-extras/manage-docs-versions",
              "sidebar": "tutorialSidebar"
            },
            {
              "id": "tutorial-extras/translate-your-site",
              "path": "/docs/next/tutorial-extras/translate-your-site",
              "sidebar": "tutorialSidebar"
            },
            {
              "id": "/category/rpc-netty-framework-20",
              "path": "/docs/next/category/rpc-netty-framework-20",
              "sidebar": "tutorialSidebar"
            },
            {
              "id": "/category/rpc-netty-framework-30",
              "path": "/docs/next/category/rpc-netty-framework-30",
              "sidebar": "tutorialSidebar"
            },
            {
              "id": "/category/tutorial---basics",
              "path": "/docs/next/category/tutorial---basics",
              "sidebar": "tutorialSidebar"
            },
            {
              "id": "/category/tutorial---extras",
              "path": "/docs/next/category/tutorial---extras",
              "sidebar": "tutorialSidebar"
            }
          ],
          "draftIds": [],
          "sidebars": {
            "tutorialSidebar": {
              "link": {
                "path": "/docs/next/rnf-intro",
                "label": "rnf-intro"
              }
            }
          }
        },
        {
          "name": "2.0",
          "label": "2.0",
          "isLast": true,
          "path": "/docs",
          "mainDocId": "rnf-intro",
          "docs": [
            {
              "id": "intro",
              "path": "/docs/intro",
              "sidebar": "tutorialSidebar"
            },
            {
              "id": "rnf-intro",
              "path": "/docs/rnf-intro",
              "sidebar": "tutorialSidebar"
            },
            {
              "id": "rpc-netty-framework-2.0/congratulations",
              "path": "/docs/rpc-netty-framework-2.0/congratulations",
              "sidebar": "tutorialSidebar"
            },
            {
              "id": "rpc-netty-framework-2.0/create-a-blog-post",
              "path": "/docs/rpc-netty-framework-2.0/create-a-blog-post",
              "sidebar": "tutorialSidebar"
            },
            {
              "id": "rpc-netty-framework-2.0/create-a-document",
              "path": "/docs/rpc-netty-framework-2.0/create-a-document",
              "sidebar": "tutorialSidebar"
            },
            {
              "id": "rpc-netty-framework-2.0/create-a-page",
              "path": "/docs/rpc-netty-framework-2.0/create-a-page",
              "sidebar": "tutorialSidebar"
            },
            {
              "id": "rpc-netty-framework-2.0/deploy-your-site",
              "path": "/docs/rpc-netty-framework-2.0/deploy-your-site",
              "sidebar": "tutorialSidebar"
            },
            {
              "id": "rpc-netty-framework-2.0/markdown-features",
              "path": "/docs/rpc-netty-framework-2.0/markdown-features",
              "sidebar": "tutorialSidebar"
            },
            {
              "id": "rpc-netty-framework-3.0/congratulations",
              "path": "/docs/rpc-netty-framework-3.0/congratulations",
              "sidebar": "tutorialSidebar"
            },
            {
              "id": "rpc-netty-framework-3.0/create-a-blog-post",
              "path": "/docs/rpc-netty-framework-3.0/create-a-blog-post",
              "sidebar": "tutorialSidebar"
            },
            {
              "id": "rpc-netty-framework-3.0/create-a-document",
              "path": "/docs/rpc-netty-framework-3.0/create-a-document",
              "sidebar": "tutorialSidebar"
            },
            {
              "id": "rpc-netty-framework-3.0/create-a-page",
              "path": "/docs/rpc-netty-framework-3.0/create-a-page",
              "sidebar": "tutorialSidebar"
            },
            {
              "id": "rpc-netty-framework-3.0/deploy-your-site",
              "path": "/docs/rpc-netty-framework-3.0/deploy-your-site",
              "sidebar": "tutorialSidebar"
            },
            {
              "id": "rpc-netty-framework-3.0/markdown-features",
              "path": "/docs/rpc-netty-framework-3.0/markdown-features",
              "sidebar": "tutorialSidebar"
            },
            {
              "id": "tutorial-basics/congratulations",
              "path": "/docs/tutorial-basics/congratulations",
              "sidebar": "tutorialSidebar"
            },
            {
              "id": "tutorial-basics/create-a-blog-post",
              "path": "/docs/tutorial-basics/create-a-blog-post",
              "sidebar": "tutorialSidebar"
            },
            {
              "id": "tutorial-basics/create-a-document",
              "path": "/docs/tutorial-basics/create-a-document",
              "sidebar": "tutorialSidebar"
            },
            {
              "id": "tutorial-basics/create-a-page",
              "path": "/docs/tutorial-basics/create-a-page",
              "sidebar": "tutorialSidebar"
            },
            {
              "id": "tutorial-basics/deploy-your-site",
              "path": "/docs/tutorial-basics/deploy-your-site",
              "sidebar": "tutorialSidebar"
            },
            {
              "id": "tutorial-basics/markdown-features",
              "path": "/docs/tutorial-basics/markdown-features",
              "sidebar": "tutorialSidebar"
            },
            {
              "id": "tutorial-extras/manage-docs-versions",
              "path": "/docs/tutorial-extras/manage-docs-versions",
              "sidebar": "tutorialSidebar"
            },
            {
              "id": "tutorial-extras/translate-your-site",
              "path": "/docs/tutorial-extras/translate-your-site",
              "sidebar": "tutorialSidebar"
            },
            {
              "id": "/category/rpc-netty-framework-20",
              "path": "/docs/category/rpc-netty-framework-20",
              "sidebar": "tutorialSidebar"
            },
            {
              "id": "/category/rpc-netty-framework-30",
              "path": "/docs/category/rpc-netty-framework-30",
              "sidebar": "tutorialSidebar"
            },
            {
              "id": "/category/tutorial---basics",
              "path": "/docs/category/tutorial---basics",
              "sidebar": "tutorialSidebar"
            },
            {
              "id": "/category/tutorial---extras",
              "path": "/docs/category/tutorial---extras",
              "sidebar": "tutorialSidebar"
            }
          ],
          "draftIds": [],
          "sidebars": {
            "tutorialSidebar": {
              "link": {
                "path": "/docs/rnf-intro",
                "label": "rnf-intro"
              }
            }
          }
        }
      ],
      "breadcrumbs": true
    }
  }
}